blacksea_cli/__init__.py
blacksea_cli/execution_manager.py
blacksea_tester-0.0.6.data/scripts/blacksea-cli
blacksea_tester-0.0.6.dist-info/DESCRIPTION.rst
blacksea_tester-0.0.6.dist-info/METADATA
blacksea_tester-0.0.6.dist-info/RECORD
blacksea_tester-0.0.6.dist-info/WHEEL
blacksea_tester-0.0.6.dist-info/metadata.json
blacksea_tester-0.0.6.dist-info/top_level.txt
