Metadata-Version: 2.0
Name: blacksea-tester
Version: 0.0.6
Summary: ATG Blacksea Test Framework client package
Home-page: https://gitlabe2.ext.net.nokia.com/atg/blacksea/blacksea-tester
Author: Umut Karabudak
Author-email: umut.karabudak@nokia.com
License: UNKNOWN
Platform: UNKNOWN
Classifier: Programming Language :: Python :: 3
Classifier: License :: Nokia Open Source License (NOKOS)
Classifier: Operating System :: OS Independent
Requires-Dist: PyYAML (==5.4.1)
Requires-Dist: Pygments (==2.9.0)
Requires-Dist: SecretStorage (==3.3.1)
Requires-Dist: bleach (==3.3.0)
Requires-Dist: certifi (==2020.12.5)
Requires-Dist: cffi (==1.14.5)
Requires-Dist: chardet (==4.0.0)
Requires-Dist: click (==7.1.2)
Requires-Dist: colorama (==0.4.4)
Requires-Dist: cryptography (==3.4.7)
Requires-Dist: docutils (==0.17.1)
Requires-Dist: idna (==2.10)
Requires-Dist: importlib-metadata (==4.0.1)
Requires-Dist: jeepney (==0.6.0)
Requires-Dist: keyring (==23.0.1)
Requires-Dist: packaging (==20.9)
Requires-Dist: pkginfo (==1.7.0)
Requires-Dist: pyaml (==20.4.0)
Requires-Dist: pycparser (==2.20)
Requires-Dist: pyparsing (==2.4.7)
Requires-Dist: readme-renderer (==29.0)
Requires-Dist: requests-toolbelt (==0.9.1)
Requires-Dist: requests (==2.25.1)
Requires-Dist: responses (==0.13.3)
Requires-Dist: rfc3986 (==1.5.0)
Requires-Dist: six (==1.16.0)
Requires-Dist: tqdm (==4.60.0)
Requires-Dist: twine (==3.4.1)
Requires-Dist: typing-extensions (==3.10.0.0)
Requires-Dist: urllib3 (==1.26.4)
Requires-Dist: webencodings (==0.5.1)
Requires-Dist: zipp (==3.4.1)
